{
  "fluentMethods": true,
  "clientRootFolder": "",
  "relationships": [
    {
      "relationshipName": "user",
      "otherEntityName": "user",
      "relationshipType": "one-to-one",
      "otherEntityField": "login",
      "ownerSide": true,
      "useJPADerivedIdentifier": false,
      "otherEntityRelationshipName": "wineCustomer"
    }
  ],
  "fields": [
    {
      "fieldName": "address",
      "fieldType": "String"
    },
    {
      "fieldName": "phone",
      "fieldType": "String"
    }
  ],
  "changelogDate": "20200607190830",
  "dto": "mapstruct",
  "searchEngine": false,
  "service": "serviceImpl",
  "entityTableName": "wine_customer",
  "databaseType": "sql",
  "readOnly": false,
  "jpaMetamodelFiltering": true,
  "pagination": "pagination"
}
